cua_operator/bridges/__init__.py
cua_operator/bridges/base.py
cua_operator/bridges/openai.py
cua_operator/contracts/action.py
cua_operator/operators/__init__.py
cua_operator/operators/common.py
cua_operator/operators/local.py
cua_operator/operators/remote_client.py
cua_operator/operators/remote_server.py
cua_operator/tools/__init__.py
cua_operator/tools/darwin.py
cua_operator/tools/win32.py
cua_operator-0.0.1.dist-info/licenses/LICENSE
cua_operator-0.0.1.dist-info/METADATA
cua_operator-0.0.1.dist-info/WHEEL
cua_operator-0.0.1.dist-info/top_level.txt
cua_operator-0.0.1.dist-info/RECORD
