Metadata-Version: 2.4
Name: cua-operator
Version: 0.0.1
Summary: Computer-Using Agent (CUA) Operator
Requires-Python: >=3.8
License-File: LICENSE
Requires-Dist: pillow
Provides-Extra: test
Requires-Dist: pytest; extra == "test"
Requires-Dist: pytest-asyncio; extra == "test"
Requires-Dist: openai; extra == "test"
Dynamic: license-file
